kindergarten/__init__.py
kindergarten/constants.py
kindergarten/core.py
kindergarten/graph_options.py
kindergarten/tab.py
kindergarten-0.0.7.dist-info/LICENSE
kindergarten-0.0.7.dist-info/METADATA
kindergarten-0.0.7.dist-info/WHEEL
kindergarten-0.0.7.dist-info/top_level.txt
kindergarten-0.0.7.dist-info/RECORD
