Metadata-Version: 2.1
Name: kindergarten
Version: 0.0.7
Summary: Kindergarten is a UI on top of Plotly to easily visualize Pandas DataFrames.
Home-page: https://github.com/henrifroese/kindergarten
Author: Henri Froese
Author-email: henri.froese@yahoo.com
License: MIT license
Keywords: kindergarten
Classifier: Development Status :: 2 - Pre-Alpha
Classifier: Intended Audience :: Developers
Classifier: License :: OSI Approved :: MIT License
Classifier: Natural Language :: English
Classifier: Programming Language :: Python :: 3
Classifier: Programming Language :: Python :: 3.7
Classifier: Programming Language :: Python :: 3.8
Requires-Python: >=3.7
License-File: LICENSE
Requires-Dist: dash-bootstrap-components (>=1.2.0)
Requires-Dist: dash (>=2.6.0)
Requires-Dist: pandas (>=1.3.5)
Requires-Dist: plotly (>=5.9.0)
Requires-Dist: jupyter-dash (>=0.4.2)
